aikernel/__init__.py
aikernel/errors.py
aikernel/py.typed
aikernel/_internal/__init__.py
aikernel/_internal/conversation.py
aikernel/_internal/router.py
aikernel/_internal/structured.py
aikernel/_internal/tools.py
aikernel/_internal/unstructured.py
aikernel/_internal/prompts/__init__.py
aikernel/_internal/prompts/fewshot.py
aikernel/_internal/types/__init__.py
aikernel/_internal/types/provider.py
aikernel/_internal/types/request.py
aikernel/_internal/types/response.py
aikernel-0.2.1.dist-info/METADATA
aikernel-0.2.1.dist-info/WHEEL
aikernel-0.2.1.dist-info/RECORD
