Metadata-Version: 2.4
Name: aikernel
Version: 0.2.1
Summary: A collection of types and interfaces for building type-safe AI tooling. Wraps around litellm.
Author-email: Nash Taylor <nash@chelle.ai>, Joshua Cook <joshua@chelle.ai>, Michael Sankur <michael@chelle.ai>
Requires-Python: >=3.12
Requires-Dist: litellm>=1.64.1
Requires-Dist: pydantic>=2.8.2
